src/salesforce/__init__.py
src/salesforce/server.py
mcp_salesforce_connector-0.1.9.dist-info/METADATA
mcp_salesforce_connector-0.1.9.dist-info/WHEEL
mcp_salesforce_connector-0.1.9.dist-info/entry_points.txt
mcp_salesforce_connector-0.1.9.dist-info/licenses/LICENSE
mcp_salesforce_connector-0.1.9.dist-info/RECORD
